{
  "4d63.com/gocheckcompilerdirectives": "MIT",
  "4d63.com/gochecknoglobals": "MIT",
  "actions/cache": "MIT",
  "actions/cache/restore": "MIT",
  "actions/checkout": "MIT",
  "actions/download-artifact": "MIT",
  "actions/github-script": "MIT",
  "actions/setup-go": "MIT",
  "actions/setup-node": "MIT",
  "actions/setup-python": "MIT",
  "aws-actions/configure-aws-credentials": "MIT",
  "actions/create-github-app-token": "MIT",
  "CycloneDX/gh-gomod-generate-sbom": "Apache-2.0",
  "dario.cat/mergo": "BSD-3-Clause",
  "github.com/andybalholm/brotli": "MIT",
  "github.com/Azure/go-ansiterm": "MIT",
  "github.com/cenkalti/backoff/v4": "MIT",
  "github.com/ClickHouse/ch-go": "Apache-2.0",
  "github.com/containerd/errdefs": "Apache-2.0",
  "github.com/containerd/errdefs/pkg": "Apache-2.0",
  "github.com/containerd/log": "Apache-2.0",
  "github.com/containerd/platforms": "Apache-2.0",
  "github.com/cpuguy83/dockercfg": "MIT",
  "github.com/davecgh/go-spew": "ISC",
  "github.com/distribution/reference": "Apache-2.0",
  "github.com/docker/docker": "Apache-2.0",
  "github.com/docker/go-connections": "Apache-2.0",
  "github.com/docker/go-units": "Apache-2.0",
  "github.com/ebitengine/purego": "Apache-2.0",
  "github.com/felixge/httpsnoop": "MIT",
  "github.com/go-faster/city": "MIT",
  "github.com/go-faster/errors": "BSD-3-Clause",
  "github.com/go-logr/logr": "Apache-2.0",
  "github.com/go-logr/stdr": "Apache-2.0",
  "github.com/go-ole/go-ole": "MIT",
  "github.com/gogo/protobuf": "BSD-3-Clause",
  "github.com/google/uuid": "BSD-3-Clause",
  "github.com/gorilla/websocket": "BSD-2-Clause",
  "github.com/Microsoft/go-winio": "MIT",
  "RoryCrispin/gh-action-bump-version": "MIT"
}
